libformat_json.so
libflow_to_graph.so
amanogawa.cpython-36m-x86_64-linux-gnu.so
libconfluence_key.so
libformat_csv.so
libbranch_column.so
libformat_xml.so
libsource_file.so
libflow_filter.so
libsink_file.so
.libslibformat_csv/libc++-b95bb561.so.1.0
.libslibformat_csv/libboost_system-mt-17b0dd51.so.1.48.0
.libslibformat_csv/libc++abi-7b48e106.so.1.0
.libslibformat_csv/libboost_filesystem-mt-c8568645.so.1.48.0
.libslibbranch_column/libc++-b95bb561.so.1.0
.libslibbranch_column/libboost_system-mt-17b0dd51.so.1.48.0
.libslibbranch_column/libc++abi-7b48e106.so.1.0
.libslibbranch_column/libboost_filesystem-mt-c8568645.so.1.48.0
.libslibflow_to_graph/libmecab-5081f6b9.so.2.0.0
.libslibflow_to_graph/libc++-b95bb561.so.1.0
.libslibflow_to_graph/libboost_system-mt-17b0dd51.so.1.48.0
.libslibflow_to_graph/libc++abi-7b48e106.so.1.0
.libslibflow_to_graph/libboost_filesystem-mt-c8568645.so.1.48.0
.libslibformat_xml/libc++-b95bb561.so.1.0
.libslibformat_xml/libboost_system-mt-17b0dd51.so.1.48.0
.libslibformat_xml/libc++abi-7b48e106.so.1.0
.libslibformat_xml/libboost_filesystem-mt-c8568645.so.1.48.0
.libslibformat_json/libc++-b95bb561.so.1.0
.libslibformat_json/libboost_system-mt-17b0dd51.so.1.48.0
.libslibformat_json/libc++abi-7b48e106.so.1.0
.libslibformat_json/libboost_filesystem-mt-c8568645.so.1.48.0
.libslibflow_filter/libc++-b95bb561.so.1.0
.libslibflow_filter/libboost_system-mt-17b0dd51.so.1.48.0
.libslibflow_filter/libc++abi-7b48e106.so.1.0
.libslibflow_filter/libboost_filesystem-mt-c8568645.so.1.48.0
.libslibsource_file/libc++-b95bb561.so.1.0
.libslibsource_file/libboost_system-mt-17b0dd51.so.1.48.0
.libslibsource_file/libc++abi-7b48e106.so.1.0
.libslibsource_file/libboost_filesystem-mt-c8568645.so.1.48.0
amanogawa-0.0.1a1.dist-info/WHEEL
amanogawa-0.0.1a1.dist-info/top_level.txt
amanogawa-0.0.1a1.dist-info/METADATA
amanogawa-0.0.1a1.dist-info/RECORD
.libslibconfluence_key/libc++-b95bb561.so.1.0
.libslibconfluence_key/libboost_system-mt-17b0dd51.so.1.48.0
.libslibconfluence_key/libc++abi-7b48e106.so.1.0
.libslibconfluence_key/libboost_filesystem-mt-c8568645.so.1.48.0
