Metadata-Version: 2.1
Name: amanogawa
Version: 0.0.1a1
Summary: Flexible graph construction and data pre-processing engine
Home-page: https://github.com/hoshizora-project/amanogawa
Author: amaya
Author-email: mail@sapphire.in.net
License: Apache2.0
Keywords: graph graph-processing graph-construction data-processing
Platform: UNKNOWN
